caselaw_test/__init__.py
caselaw_test/functions.py
caselaw_test-0.1.0.dist-info/METADATA
caselaw_test-0.1.0.dist-info/WHEEL
caselaw_test-0.1.0.dist-info/top_level.txt
caselaw_test-0.1.0.dist-info/RECORD
